cressent/__init__.py
cressent/cli.py
cressent/cressent.py
cressent/modules/__init__.py
cressent/modules/adjust_seq.py
cressent/modules/align.py
cressent/modules/anicalc.py
cressent/modules/aniclust.py
cressent/modules/args.py
cressent/modules/build_contaminant_db.py
cressent/modules/build_tree.py
cressent/modules/cluster.py
cressent/modules/cruise.py
cressent/modules/db_builder.py
cressent/modules/detect_contamination.py
cressent/modules/gc_ht.py
cressent/modules/gene_map.R
cressent/modules/gene_map.py
cressent/modules/motif.py
cressent/modules/motif_disc.py
cressent/modules/motif_map_viz.py
cressent/modules/plot_tree.R
cressent/modules/plot_tree.py
cressent/modules/pos_stem_loop.py
cressent/modules/recombination.py
cressent/modules/run_cruise.py
cressent/modules/seq_logo.R
cressent/modules/seq_logo.py
cressent/modules/sl_finder.py
cressent/modules/tanglegram.R
cressent/modules/tanglegram.py
cressent/modules/openrdp/__init__.py
cressent/modules/openrdp/__main__.py
cressent/modules/openrdp/main.py
cressent/modules/openrdp/bin/__init__.py
cressent/modules/openrdp/bin/3Seq/3seq.Unix
cressent/modules/openrdp/bin/3Seq/__init__.py
cressent/modules/openrdp/bin/3Seq/myPvalueTable
cressent/modules/openrdp/bin/GENECONV/__init__.py
cressent/modules/openrdp/bin/GENECONV/geneconv.Unix
cressent/modules/openrdp/bin/source_code/3seq_build_170612.zip
cressent/modules/openrdp/bin/source_code/LICENSE.md
cressent/modules/openrdp/bin/source_code/__init__.py
cressent/modules/openrdp/bin/source_code/geneconv_unix.source.tar
cressent/modules/openrdp/bin/source_code/myPvalueTable.tar.gz
cressent/modules/openrdp/scripts/__init__.py
cressent/modules/openrdp/scripts/bootscan.py
cressent/modules/openrdp/scripts/chimaera.py
cressent/modules/openrdp/scripts/common.py
cressent/modules/openrdp/scripts/default_config.ini
cressent/modules/openrdp/scripts/geneconv.py
cressent/modules/openrdp/scripts/maxchi.py
cressent/modules/openrdp/scripts/preprocessing.py
cressent/modules/openrdp/scripts/rdp.py
cressent-1.0.0.dist-info/licenses/LICENSE
cressent-1.0.0.dist-info/METADATA
cressent-1.0.0.dist-info/WHEEL
cressent-1.0.0.dist-info/entry_points.txt
cressent-1.0.0.dist-info/top_level.txt
cressent-1.0.0.dist-info/RECORD
