Metadata-Version: 2.4
Name: cressent
Version: 1.0.0
Summary: A comprehensive toolkit for ssDNA virus analysis
Author-email: "Pavan R. & Tisza M." <pavan.4@osu.edu>
License: MIT License
Project-URL: Homepage, https://github.com/ricrocha82/cressent
Project-URL: Repository, https://github.com/ricrocha82/cressent
Requires-Python: >=3.6
License-File: LICENSE
Requires-Dist: biopython
Requires-Dist: pandas
Requires-Dist: click
Dynamic: license-file
